LAB4_LOCAL/ALU.sv
module ALU #(
    parameter DATA_WIDTH = 32
)(
    input logic [DATA_WIDTH-1:0] ALUop1,
    input logic [DATA_WIDTH-1:0] ALUop2,
    //input logic ALUctrl,
    output logic [DATA_WIDTH-1:0] ALUout,
    output logic EQ 
);

assign EQ = (ALUop1==ALUop2);
assign ALUout = ALUop1 + ALUop2;

endmodule

LAB4_LOCAL/Reg_file.sv
module Reg_file #(
    parameter DATA_WIDTH = 32,
              ADD_WIDTH = 5
)(
    input logic [ADD_WIDTH-1:0] AD1,
    input logic [ADD_WIDTH-1:0] AD2,
    input logic [ADD_WIDTH-1:0] AD3,
    input logic [DATA_WIDTH-1:0] WD3,
    input logic WE3,
    input clk,
    output logic [DATA_WIDTH-1:0] RD1,
    output logic [DATA_WIDTH-1:0] RD2,
    output [DATA_WIDTH-1:0] a0, 
    output [DATA_WIDTH-1:0] a1    // added for debugging
);

logic [DATA_WIDTH-1:0] register [2**ADD_WIDTH-1:0];

// CHANGE NEEDED: read - async; write - sync
always_ff @(posedge clk) begin
    RD1 <= register[AD1];
    RD2 <= register[AD2];
    if(WE3) register[AD3] <= WD3;
    a0 <= register[5'd10];
    a1 <= register[5'd11];    // added for debugging
end

endmodule

LAB4_LOCAL/part2_top.sv
module part2_top #(
    parameter DATA_WIDTH = 32,
              ADD_WIDTH = 5
)(
    input logic clk,
    input logic [ADD_WIDTH-1:0] AD1,
    input logic [ADD_WIDTH-1:0] AD2,
    input logic [ADD_WIDTH-1:0] AD3,
    input logic WE3,
    input logic ALUsrc,
    input logic [DATA_WIDTH-1:0] Immop,
    output logic EQ,
    output logic [DATA_WIDTH-1:0] a0,
    output logic [DATA_WIDTH-1:0] a1    // added for debugging
);

logic [DATA_WIDTH-1:0] RD1, RD2, ALUop2, ALUOUT;

Reg_file REG (
    .AD1(AD1),
    .AD2(AD2),
    .AD3(AD3),
    .WE3(WE3),
    .WD3(ALUOUT),
    .clk(clk),
    .a0(a0),
    .a1(a1),    // added for debugging
    .RD1(RD1),
    .RD2(RD2)
);

ALU ALU1 (
    .ALUop1(RD1),
    .ALUop2(ALUop2),
    .ALUout(ALUOUT),
    .EQ(EQ)
);

assign ALUop2 = ALUsrc? Immop:RD2;

endmodule

Lab4-Reduced-RISC-V-with-lw/signExtend.sv
module signExtend #(
    parameter WIDTH = 32
)(
    input logic  [WIDTH-1:0]  instr,
    input logic               ImmSrc,
    output logic [WIDTH-1:0]  ImmOp
);

    always_comb 
        case (ImmSrc)
            1'b0:          ImmOp = {{20{instr[31]}},instr[31:20]};  // IMMEDIATE
            // 3'b000:     ImmOp = {instr[31:12], 12{1'b0}};                //UPPER IMMEDIATE
            // 3'b000:     ImmOp = {20{instr[31]}, instr[31:25], intr[11:7]};       //STORE
            1'b1:          ImmOp = {{21{instr[31]}}, instr[7], instr[30:25], instr[11:8]};  // BRANCH
        endcase
endmodule

LAB4_LOCAL/controlUnit.sv
module controlUnit #(
    parameter WIDTH = 32
)(
    input logic  [WIDTH-1:0]    instr,
    input logic                 Eq,
    output logic                RegWrite,
    //output logic [2:0]          ALUctrl,
    output logic                ALUsrc,
    output logic                ImmSrc,
    output logic                PCsrc
);

    always @ (instr) begin
        
        // addi
        if (instr[6:0] == 7'b0010011 && instr[14:12] == 3'b000) begin
            RegWrite <= 1'b1;
            // ALUctrl <= 1'b1;
            ALUsrc <= 1'b1;
            ImmSrc <= 1'b0;
            PCsrc <= 1'b0;
        end

        // bne
        if (instr[6:0] == 7'b1100011 && instr[14:12] == 3'b001) begin
            RegWrite <= 1'b0;
            // ALUctrl <= 1'b1;
            ALUsrc <= 1'b0;
            ImmSrc <= 1'b1;
            PCsrc <= Eq ? 1'b0 : 1'b1;  // branch if not equal
        end
    end

endmodule

LAB4_LOCAL/instrMem.sv
module instrMem #(
    parameter WIDTH = 32
)(
    input logic [WIDTH - 1 : 0] A,
    output logic [WIDTH - 1: 0] RD

);

logic [7:0] rom_array [2**10-1:0];

initial begin
    $display("Loading ROM.");
    $readmemh("instrRom.mem", rom_array);
end;

always_comb
    //output is asynchronus
    RD = {rom_array[{A+{{30{1'b0}}, 2'b11}}], rom_array[{A+{{30{1'b0}}, 2'b10}}] ,rom_array[{A+{{31{1'b0}}, 1'b1}}], rom_array[A]};

endmodule

LAB4_LOCAL/PC_REG.sv
module PC_REG #(
    parameter ADD_WIDTH = 32
)(
    input [ADD_WIDTH-1:0] Immop,
    input pcsrc,
    input clk,
    input rst,
    output [ADD_WIDTH-1:0] PC
);

logic [ADD_WIDTH-1:0] branch_pc, inc_pc, next_pc, tmp_pc;

assign branch_pc = tmp_pc + Immop;
assign inc_pc = tmp_pc + 32'd4;

assign next_pc = pcsrc ? branch_pc : inc_pc;

always_ff @(posedge clk) begin
    if (!rst)
        tmp_pc <= next_pc;
    else
        tmp_pc <= 32'b0;
end

assign PC = tmp_pc;
endmodule

LAB4_LOCAL/cpu.sv
module cpu #(
    parameter A_WIDTH = 32,
              D_WIDTH = 32,
              rs1_LSB = 15,
              rs2_LSB = 20,
              rd_LSB = 7,
              ADD_WIDTH = 5
)(
    /// interface signals
    input logic                 clk,
    input logic                 rst,

    // data outputs from register file
    output logic [D_WIDTH-1:0]  a0, 
    output logic [D_WIDTH-1:0]  a1    // added for debugging
);

    /// interconnect wires
    logic   [A_WIDTH-1:0]        pc;      // program counter (PC)
    logic   [D_WIDTH-1:0]        instr;   // instruction
    logic   [D_WIDTH-1:0]        ImmOp;   // immediate operand (sign-extended)
        /// Control Unit outputs:
    logic                        RegWrite;
    logic                        ALUctrl;
    logic                        ALUsrc;
    logic                        ImmSrc;    // logic   [1:0]                ImmSrc;
    logic                        PCsrc;
        /// ALU block outputs:
 // logic   [D_WIDTH-1:0]        ALUout;    // already wired up inside
    logic                        eq;        // EQ

PC_REG PC_Reg (
    /// input
    .clk (clk),     // PC Reg clock
    .rst (rst),     // PC Reg reset
    .Immop (ImmOp),
    .pcsrc(PCsrc),
    /// output
    .PC (pc)
);

instrMem instr_mem (
    // input
    .A (pc),
    // output
    .RD (instr)
);

controlUnit control_unit (
    /// input
    .Eq (eq),
    .instr (instr),
    /// output
    .RegWrite (RegWrite),
    // .ALUctrl (ALUctrl),
    .ALUsrc (ALUsrc),
    .ImmSrc (ImmSrc),
    .PCsrc (PCsrc)
);

signExtend sign_extend(
    /// input
    .instr (instr),
    .ImmSrc (ImmSrc),
    /// output
    .ImmOp (ImmOp)
);

part2_top reg_file_alu (
    /// input 
    .clk (clk),              // Reg File clock
    .AD1 (instr[rs1_LSB+ADD_WIDTH-1 : rs1_LSB]),     // rs1 = instr[19:15]
    .AD2 (instr[rs2_LSB+ADD_WIDTH-1 : rs2_LSB]),     // rs2 = instr[24:20]
    .AD3 (instr[rd_LSB+ADD_WIDTH-1 : rd_LSB]),       //  rd = instr[11:7]
    .WE3 (RegWrite),
    // .WD3 (ALUout),      // already wired up inside
    .ALUsrc (ALUsrc),
    // .ALUctrl (ALUctrl),
    .Immop (ImmOp),
    /// output
    // .ALUout (ALUout),   // already wired up inside
    .EQ (eq),
    .a0 (a0),
    .a1(a1)    // added for debugging
);

endmodule

LAB4_LOCAL/cpu.vcd
$version Generated by VerilatedVcd $end
$date Fri Nov 25 10:38:15 2022 $end
$timescale 1ps $end

 $scope module TOP $end
  $var wire 32 W a0 [31:0] $end
  $var wire 32 X a1 [31:0] $end
  $var wire  1 U clk $end
  $var wire  1 V rst $end
  $scope module cpu $end
   $var wire 32 ] ADD_WIDTH [31:0] $end
   $var wire  1 ^ ALUctrl $end
   $var wire  1 ' ALUsrc $end
   $var wire 32 Y A_WIDTH [31:0] $end
   $var wire 32 Y D_WIDTH [31:0] $end
   $var wire 32 % ImmOp [31:0] $end
   $var wire  1 ( ImmSrc $end
   $var wire  1 ) PCsrc $end
   $var wire  1 & RegWrite $end
   $var wire 32 W a0 [31:0] $end
   $var wire 32 X a1 [31:0] $end
   $var wire  1 U clk $end
   $var wire  1 * eq $end
   $var wire 32 $ instr [31:0] $end
   $var wire 32 # pc [31:0] $end
   $var wire 32 \ rd_LSB [31:0] $end
   $var wire 32 Z rs1_LSB [31:0] $end
   $var wire 32 [ rs2_LSB [31:0] $end
   $var wire  1 V rst $end
   $scope module PC_Reg $end
    $var wire 32 Y ADD_WIDTH [31:0] $end
    $var wire 32 % Immop [31:0] $end
    $var wire 32 # PC [31:0] $end
    $var wire 32 + branch_pc [31:0] $end
    $var wire  1 U clk $end
    $var wire 32 , inc_pc [31:0] $end
    $var wire 32 - next_pc [31:0] $end
    $var wire  1 ) pcsrc $end
    $var wire  1 V rst $end
    $var wire 32 # tmp_pc [31:0] $end
   $upscope $end
   $scope module control_unit $end
    $var wire  1 ' ALUsrc $end
    $var wire  1 * Eq $end
    $var wire  1 ( ImmSrc $end
    $var wire  1 ) PCsrc $end
    $var wire  1 & RegWrite $end
    $var wire 32 Y WIDTH [31:0] $end
    $var wire 32 $ instr [31:0] $end
   $upscope $end
   $scope module instr_mem $end
    $var wire 32 # A [31:0] $end
    $var wire 32 $ RD [31:0] $end
    $var wire 32 Y WIDTH [31:0] $end
   $upscope $end
   $scope module reg_file_alu $end
    $var wire  5 . AD1 [4:0] $end
    $var wire  5 / AD2 [4:0] $end
    $var wire  5 0 AD3 [4:0] $end
    $var wire 32 ] ADD_WIDTH [31:0] $end
    $var wire 32 4 ALUOUT [31:0] $end
    $var wire 32 3 ALUop2 [31:0] $end
    $var wire  1 ' ALUsrc $end
    $var wire 32 Y DATA_WIDTH [31:0] $end
    $var wire  1 * EQ $end
    $var wire 32 % Immop [31:0] $end
    $var wire 32 1 RD1 [31:0] $end
    $var wire 32 2 RD2 [31:0] $end
    $var wire  1 & WE3 $end
    $var wire 32 W a0 [31:0] $end
    $var wire 32 X a1 [31:0] $end
    $var wire  1 U clk $end
    $scope module ALU1 $end
     $var wire 32 1 ALUop1 [31:0] $end
     $var wire 32 3 ALUop2 [31:0] $end
     $var wire 32 4 ALUout [31:0] $end
     $var wire 32 Y DATA_WIDTH [31:0] $end
     $var wire  1 * EQ $end
    $upscope $end
    $scope module REG $end
     $var wire  5 . AD1 [4:0] $end
     $var wire  5 / AD2 [4:0] $end
     $var wire  5 0 AD3 [4:0] $end
     $var wire 32 ] ADD_WIDTH [31:0] $end
     $var wire 32 Y DATA_WIDTH [31:0] $end
     $var wire 32 1 RD1 [31:0] $end
     $var wire 32 2 RD2 [31:0] $end
     $var wire 32 4 WD3 [31:0] $end
     $var wire  1 & WE3 $end
     $var wire 32 W a0 [31:0] $end
     $var wire 32 X a1 [31:0] $end
     $var wire  1 U clk $end
     $var wire 32 5 register[0] [31:0] $end
     $var wire 32 ? register[10] [31:0] $end
     $var wire 32 @ register[11] [31:0] $end
     $var wire 32 A register[12] [31:0] $end
     $var wire 32 B register[13] [31:0] $end
     $var wire 32 C register[14] [31:0] $end
     $var wire 32 D register[15] [31:0] $end
     $var wire 32 E register[16] [31:0] $end
     $var wire 32 F register[17] [31:0] $end
     $var wire 32 G register[18] [31:0] $end
     $var wire 32 H register[19] [31:0] $end
     $var wire 32 6 register[1] [31:0] $end
     $var wire 32 I register[20] [31:0] $end
     $var wire 32 J register[21] [31:0] $end
     $var wire 32 K register[22] [31:0] $end
     $var wire 32 L register[23] [31:0] $end
     $var wire 32 M register[24] [31:0] $end
     $var wire 32 N register[25] [31:0] $end
     $var wire 32 O register[26] [31:0] $end
     $var wire 32 P register[27] [31:0] $end
     $var wire 32 Q register[28] [31:0] $end
     $var wire 32 R register[29] [31:0] $end
     $var wire 32 7 register[2] [31:0] $end
     $var wire 32 S register[30] [31:0] $end
     $var wire 32 T register[31] [31:0] $end
     $var wire 32 8 register[3] [31:0] $end
     $var wire 32 9 register[4] [31:0] $end
     $var wire 32 : register[5] [31:0] $end
     $var wire 32 ; register[6] [31:0] $end
     $var wire 32 < register[7] [31:0] $end
     $var wire 32 = register[8] [31:0] $end
     $var wire 32 > register[9] [31:0] $end
    $upscope $end
   $upscope $end
   $scope module sign_extend $end
    $var wire 32 % ImmOp [31:0] $end
    $var wire  1 ( ImmSrc $end
    $var wire 32 Y WIDTH [31:0] $end
    $var wire 32 $ instr [31:0] $end
   $upscope $end
  $upscope $end
 $upscope $end
$enddefinitions $end


#0
b00000000000000000000000000000000 #
b00000000000000000000000000000000 $
b00000000000000000000000000000000 %
0&
0'
0(
0)
1*
b00000000000000000000000000000000 +
b00000000000000000000000000000100 ,
b00000000000000000000000000000100 -
b00000 .
b00000 /
b00000 0
b00000000000000000000000000000000 1
b00000000000000000000000000000000 2
b00000000000000000000000000000000 3
b00000000000000000000000000000000 4
b00000000000000000000000000000000 5
b00000000000000000000000000000000 6
b00000000000000000000000000000000 7
b00000000000000000000000000000000 8
b00000000000000000000000000000000 9
b00000000000000000000000000000000 :
b00000000000000000000000000000000 ;
b00000000000000000000000000000000 <
b00000000000000000000000000000000 =
b00000000000000000000000000000000 >
b00000000000000000000000000000000 ?
b00000000000000000000000000000000 @
b00000000000000000000000000000000 A
b00000000000000000000000000000000 B
b00000000000000000000000000000000 C
b00000000000000000000000000000000 D
b00000000000000000000000000000000 E
b00000000000000000000000000000000 F
b00000000000000000000000000000000 G
b00000000000000000000000000000000 H
b00000000000000000000000000000000 I
b00000000000000000000000000000000 J
b00000000000000000000000000000000 K
b00000000000000000000000000000000 L
b00000000000000000000000000000000 M
b00000000000000000000000000000000 N
b00000000000000000000000000000000 O
b00000000000000000000000000000000 P
b00000000000000000000000000000000 Q
b00000000000000000000000000000000 R
b00000000000000000000000000000000 S
b00000000000000000000000000000000 T
1U
1V
b00000000000000000000000000000000 W
b00000000000000000000000000000000 X
b00000000000000000000000000100000 Y
b00000000000000000000000000001111 Z
b00000000000000000000000000010100 [
b00000000000000000000000000000111 \
b00000000000000000000000000000101 ]
0^
#1
b00001111111100000000001100010011 $
b00000000000000000000000011111111 %
1&
1'
0*
b00000000000000000000000011111111 +
b11111 /
b00110 0
b00000000000000000000000011111111 3
b00000000000000000000000011111111 4
0U
#2
b00000000000000000000000011111111 ;
1U
#3
0U
#4
1U
#5
0U
#6
1U
0V
#7
0U
#8
b00000000000000000000000000000100 #
b00000000000000000000010100010011 $
b00000000000000000000000000000000 %
1*
b00000000000000000000000000000100 +
b00000000000000000000000000001000 ,
b00000000000000000000000000001000 -
b00000 /
b01010 0
b00000000000000000000000000000000 3
b00000000000000000000000000000000 4
1U
#9
0U
#10
b00000000000000000000000000001000 #
b00000000000000000000010110010011 $
b00000000000000000000000000001000 +
b00000000000000000000000000001100 ,
b00000000000000000000000000001100 -
b01011 0
1U
#11
0U
#12
b00000000000000000000000000001100 #
b00000000000001011000010100010011 $
b00000000000000000000000000001100 +
b00000000000000000000000000010000 ,
b00000000000000000000000000010000 -
b01011 .
b01010 0
1U
#13
0U
#14
b00000000000000000000000000010000 #
b00000000000101011000010110010011 $
b00000000000000000000000000000001 %
0*
b00000000000000000000000000010001 +
b00000000000000000000000000010100 ,
b00000000000000000000000000010100 -
b00001 /
b01011 0
b00000000000000000000000000000001 3
b00000000000000000000000000000001 4
1U
#15
0U
#16
b00000000000000000000000000010100 #
b11111110011001011001100011100011 $
b11111111111111111111111111111000 %
0&
0'
1(
1)
b00000000000000000000000000001100 +
b00000000000000000000000000011000 ,
b00000000000000000000000000001100 -
b00110 /
b10001 0
b00000000000000000000000000000001 1
b00000000000000000000000011111111 2
b00000000000000000000000011111111 3
b00000000000000000000000100000000 4
b00000000000000000000000000000001 @
1U
#17
0U
#18
b00000000000000000000000000001100 #
b00000000000001011000010100010011 $
b00000000000000000000000000000000 %
1&
1'
0(
0)
b00000000000000000000000000010000 ,
b00000000000000000000000000010000 -
b00000 /
b01010 0
b00000000000000000000000000000000 2
b00000000000000000000000000000000 3
b00000000000000000000000000000001 4
1U
b00000000000000000000000000000001 X
#19
0U
#20
b00000000000000000000000000010000 #
b00000000000101011000010110010011 $
b00000000000000000000000000000001 %
1*
b00000000000000000000000000010001 +
b00000000000000000000000000010100 ,
b00000000000000000000000000010100 -
b00001 /
b01011 0
b00000000000000000000000000000001 3
b00000000000000000000000000000010 4
b00000000000000000000000000000001 ?
1U
#21
0U
#22
b00000000000000000000000000010100 #
b11111110011001011001100011100011 $
b11111111111111111111111111111000 %
0&
0'
1(
1)
0*
b00000000000000000000000000001100 +
b00000000000000000000000000011000 ,
b00000000000000000000000000001100 -
b00110 /
b10001 0
b00000000000000000000000000000010 1
b00000000000000000000000011111111 2
b00000000000000000000000011111111 3
b00000000000000000000000100000001 4
b00000000000000000000000000000010 @
1U
b00000000000000000000000000000001 W
#23
0U
#24
b00000000000000000000000000001100 #
b00000000000001011000010100010011 $
b00000000000000000000000000000000 %
1&
1'
0(
0)
b00000000000000000000000000010000 ,
b00000000000000000000000000010000 -
b00000 /
b01010 0
b00000000000000000000000000000000 2
b00000000000000000000000000000000 3
b00000000000000000000000000000010 4
1U
b00000000000000000000000000000010 X
#25
0U
#26
b00000000000000000000000000010000 #
b00000000000101011000010110010011 $
b00000000000000000000000000000001 %
b00000000000000000000000000010001 +
b00000000000000000000000000010100 ,
b00000000000000000000000000010100 -
b00001 /
b01011 0
b00000000000000000000000000000001 3
b00000000000000000000000000000011 4
b00000000000000000000000000000010 ?
1U
#27
0U
#28
b00000000000000000000000000010100 #
b11111110011001011001100011100011 $
b11111111111111111111111111111000 %
0&
0'
1(
1)
b00000000000000000000000000001100 +
b00000000000000000000000000011000 ,
b00000000000000000000000000001100 -
b00110 /
b10001 0
b00000000000000000000000000000011 1
b00000000000000000000000011111111 2
b00000000000000000000000011111111 3
b00000000000000000000000100000010 4
b00000000000000000000000000000011 @
1U
b00000000000000000000000000000010 W
#29
0U
#30
b00000000000000000000000000001100 #
b00000000000001011000010100010011 $
b00000000000000000000000000000000 %
1&
1'
0(
0)
b00000000000000000000000000010000 ,
b00000000000000000000000000010000 -
b00000 /
b01010 0
b00000000000000000000000000000000 2
b00000000000000000000000000000000 3
b00000000000000000000000000000011 4
1U
b00000000000000000000000000000011 X
#31
0U
#32
b00000000000000000000000000010000 #
b00000000000101011000010110010011 $
b00000000000000000000000000000001 %
b00000000000000000000000000010001 +
b00000000000000000000000000010100 ,
b00000000000000000000000000010100 -
b00001 /
b01011 0
b00000000000000000000000000000001 3
b00000000000000000000000000000100 4
b00000000000000000000000000000011 ?
1U
#33
0U
#34
b00000000000000000000000000010100 #
b11111110011001011001100011100011 $
b11111111111111111111111111111000 %
0&
0'
1(
1)
b00000000000000000000000000001100 +
b00000000000000000000000000011000 ,
b00000000000000000000000000001100 -
b00110 /
b10001 0
b00000000000000000000000000000100 1
b00000000000000000000000011111111 2
b00000000000000000000000011111111 3
b00000000000000000000000100000011 4
b00000000000000000000000000000100 @
1U
b00000000000000000000000000000011 W
#35
0U
#36
b00000000000000000000000000001100 #
b00000000000001011000010100010011 $
b00000000000000000000000000000000 %
1&
1'
0(
0)
b00000000000000000000000000010000 ,
b00000000000000000000000000010000 -
b00000 /
b01010 0
b00000000000000000000000000000000 2
b00000000000000000000000000000000 3
b00000000000000000000000000000100 4
1U
b00000000000000000000000000000100 X
#37
0U
#38
b00000000000000000000000000010000 #
b00000000000101011000010110010011 $
b00000000000000000000000000000001 %
b00000000000000000000000000010001 +
b00000000000000000000000000010100 ,
b00000000000000000000000000010100 -
b00001 /
b01011 0
b00000000000000000000000000000001 3
b00000000000000000000000000000101 4
b00000000000000000000000000000100 ?
1U
#39
0U
#40
b00000000000000000000000000010100 #
b11111110011001011001100011100011 $
b11111111111111111111111111111000 %
0&
0'
1(
1)
b00000000000000000000000000001100 +
b00000000000000000000000000011000 ,
b00000000000000000000000000001100 -
b00110 /
b10001 0
b00000000000000000000000000000101 1
b00000000000000000000000011111111 2
b00000000000000000000000011111111 3
b00000000000000000000000100000100 4
b00000000000000000000000000000101 @
1U
b00000000000000000000000000000100 W
#41
0U
#42
b00000000000000000000000000001100 #
b00000000000001011000010100010011 $
b00000000000000000000000000000000 %
1&
1'
0(
0)
b00000000000000000000000000010000 ,
b00000000000000000000000000010000 -
b00000 /
b01010 0
b00000000000000000000000000000000 2
b00000000000000000000000000000000 3
b00000000000000000000000000000101 4
1U
b00000000000000000000000000000101 X
#43
0U
#44
b00000000000000000000000000010000 #
b00000000000101011000010110010011 $
b00000000000000000000000000000001 %
b00000000000000000000000000010001 +
b00000000000000000000000000010100 ,
b00000000000000000000000000010100 -
b00001 /
b01011 0
b00000000000000000000000000000001 3
b00000000000000000000000000000110 4
b00000000000000000000000000000101 ?
1U
#45
0U
#46
b00000000000000000000000000010100 #
b11111110011001011001100011100011 $
b11111111111111111111111111111000 %
0&
0'
1(
1)
b00000000000000000000000000001100 +
b00000000000000000000000000011000 ,
b00000000000000000000000000001100 -
b00110 /
b10001 0
b00000000000000000000000000000110 1
b00000000000000000000000011111111 2
b00000000000000000000000011111111 3
b00000000000000000000000100000101 4
b00000000000000000000000000000110 @
1U
b00000000000000000000000000000101 W
#47
0U
#48
b00000000000000000000000000001100 #
b00000000000001011000010100010011 $
b00000000000000000000000000000000 %
1&
1'
0(
0)
b00000000000000000000000000010000 ,
b00000000000000000000000000010000 -
b00000 /
b01010 0
b00000000000000000000000000000000 2
b00000000000000000000000000000000 3
b00000000000000000000000000000110 4
1U
b00000000000000000000000000000110 X
#49
0U
#50
b00000000000000000000000000010000 #
b00000000000101011000010110010011 $
b00000000000000000000000000000001 %
b00000000000000000000000000010001 +
b00000000000000000000000000010100 ,
b00000000000000000000000000010100 -
b00001 /
b01011 0
b00000000000000000000000000000001 3
b00000000000000000000000000000111 4
b00000000000000000000000000000110 ?
1U
#51
0U
#52
b00000000000000000000000000010100 #
b11111110011001011001100011100011 $
b11111111111111111111111111111000 %
0&
0'
1(
1)
b00000000000000000000000000001100 +
b00000000000000000000000000011000 ,
b00000000000000000000000000001100 -
b00110 /
b10001 0
b00000000000000000000000000000111 1
b00000000000000000000000011111111 2
b00000000000000000000000011111111 3
b00000000000000000000000100000110 4
b00000000000000000000000000000111 @
1U
b00000000000000000000000000000110 W
#53
0U
#54
b00000000000000000000000000001100 #
b00000000000001011000010100010011 $
b00000000000000000000000000000000 %
1&
1'
0(
0)
b00000000000000000000000000010000 ,
b00000000000000000000000000010000 -
b00000 /
b01010 0
b00000000000000000000000000000000 2
b00000000000000000000000000000000 3
b00000000000000000000000000000111 4
1U
b00000000000000000000000000000111 X
#55
0U
#56
b00000000000000000000000000010000 #
b00000000000101011000010110010011 $
b00000000000000000000000000000001 %
b00000000000000000000000000010001 +
b00000000000000000000000000010100 ,
b00000000000000000000000000010100 -
b00001 /
b01011 0
b00000000000000000000000000000001 3
b00000000000000000000000000001000 4
b00000000000000000000000000000111 ?
1U
#57
0U
#58
b00000000000000000000000000010100 #
b11111110011001011001100011100011 $
b11111111111111111111111111111000 %
0&
0'
1(
1)
b00000000000000000000000000001100 +
b00000000000000000000000000011000 ,
b00000000000000000000000000001100 -
b00110 /
b10001 0
b00000000000000000000000000001000 1
b00000000000000000000000011111111 2
b00000000000000000000000011111111 3
b00000000000000000000000100000111 4
b00000000000000000000000000001000 @
1U
b00000000000000000000000000000111 W
#59
0U
#60
b00000000000000000000000000001100 #
b00000000000001011000010100010011 $
b00000000000000000000000000000000 %
1&
1'
0(
0)
b00000000000000000000000000010000 ,
b00000000000000000000000000010000 -
b00000 /
b01010 0
b00000000000000000000000000000000 2
b00000000000000000000000000000000 3
b00000000000000000000000000001000 4
1U
b00000000000000000000000000001000 X
#61
0U
#62
b00000000000000000000000000010000 #
b00000000000101011000010110010011 $
b00000000000000000000000000000001 %
b00000000000000000000000000010001 +
b00000000000000000000000000010100 ,
b00000000000000000000000000010100 -
b00001 /
b01011 0
b00000000000000000000000000000001 3
b00000000000000000000000000001001 4
b00000000000000000000000000001000 ?
1U
#63
0U
#64
b00000000000000000000000000010100 #
b11111110011001011001100011100011 $
b11111111111111111111111111111000 %
0&
0'
1(
1)
b00000000000000000000000000001100 +
b00000000000000000000000000011000 ,
b00000000000000000000000000001100 -
b00110 /
b10001 0
b00000000000000000000000000001001 1
b00000000000000000000000011111111 2
b00000000000000000000000011111111 3
b00000000000000000000000100001000 4
b00000000000000000000000000001001 @
1U
b00000000000000000000000000001000 W
#65
0U
#66
b00000000000000000000000000001100 #
b00000000000001011000010100010011 $
b00000000000000000000000000000000 %
1&
1'
0(
0)
b00000000000000000000000000010000 ,
b00000000000000000000000000010000 -
b00000 /
b01010 0
b00000000000000000000000000000000 2
b00000000000000000000000000000000 3
b00000000000000000000000000001001 4
1U
b00000000000000000000000000001001 X
#67
0U
#68
b00000000000000000000000000010000 #
b00000000000101011000010110010011 $
b00000000000000000000000000000001 %
b00000000000000000000000000010001 +
b00000000000000000000000000010100 ,
b00000000000000000000000000010100 -
b00001 /
b01011 0
b00000000000000000000000000000001 3
b00000000000000000000000000001010 4
b00000000000000000000000000001001 ?
1U
#69
0U
#70
b00000000000000000000000000010100 #
b11111110011001011001100011100011 $
b11111111111111111111111111111000 %
0&
0'
1(
1)
b00000000000000000000000000001100 +
b00000000000000000000000000011000 ,
b00000000000000000000000000001100 -
b00110 /
b10001 0
b00000000000000000000000000001010 1
b00000000000000000000000011111111 2
b00000000000000000000000011111111 3
b00000000000000000000000100001001 4
b00000000000000000000000000001010 @
1U
b00000000000000000000000000001001 W
#71
0U
#72
b00000000000000000000000000001100 #
b00000000000001011000010100010011 $
b00000000000000000000000000000000 %
1&
1'
0(
0)
b00000000000000000000000000010000 ,
b00000000000000000000000000010000 -
b00000 /
b01010 0
b00000000000000000000000000000000 2
b00000000000000000000000000000000 3
b00000000000000000000000000001010 4
1U
b00000000000000000000000000001010 X
#73
0U
#74
b00000000000000000000000000010000 #
b00000000000101011000010110010011 $
b00000000000000000000000000000001 %
b00000000000000000000000000010001 +
b00000000000000000000000000010100 ,
b00000000000000000000000000010100 -
b00001 /
b01011 0
b00000000000000000000000000000001 3
b00000000000000000000000000001011 4
b00000000000000000000000000001010 ?
1U
#75
0U
#76
b00000000000000000000000000010100 #
b11111110011001011001100011100011 $
b11111111111111111111111111111000 %
0&
0'
1(
1)
b00000000000000000000000000001100 +
b00000000000000000000000000011000 ,
b00000000000000000000000000001100 -
b00110 /
b10001 0
b00000000000000000000000000001011 1
b00000000000000000000000011111111 2
b00000000000000000000000011111111 3
b00000000000000000000000100001010 4
b00000000000000000000000000001011 @
1U
b00000000000000000000000000001010 W
#77
0U
#78
b00000000000000000000000000001100 #
b00000000000001011000010100010011 $
b00000000000000000000000000000000 %
1&
1'
0(
0)
b00000000000000000000000000010000 ,
b00000000000000000000000000010000 -
b00000 /
b01010 0
b00000000000000000000000000000000 2
b00000000000000000000000000000000 3
b00000000000000000000000000001011 4
1U
b00000000000000000000000000001011 X
#79
0U
#80
b00000000000000000000000000010000 #
b00000000000101011000010110010011 $
b00000000000000000000000000000001 %
b00000000000000000000000000010001 +
b00000000000000000000000000010100 ,
b00000000000000000000000000010100 -
b00001 /
b01011 0
b00000000000000000000000000000001 3
b00000000000000000000000000001100 4
b00000000000000000000000000001011 ?
1U
#81
0U
#82
b00000000000000000000000000010100 #
b11111110011001011001100011100011 $
b11111111111111111111111111111000 %
0&
0'
1(
1)
b00000000000000000000000000001100 +
b00000000000000000000000000011000 ,
b00000000000000000000000000001100 -
b00110 /
b10001 0
b00000000000000000000000000001100 1
b00000000000000000000000011111111 2
b00000000000000000000000011111111 3
b00000000000000000000000100001011 4
b00000000000000000000000000001100 @
1U
b00000000000000000000000000001011 W
#83
0U
#84
b00000000000000000000000000001100 #
b00000000000001011000010100010011 $
b00000000000000000000000000000000 %
1&
1'
0(
0)
b00000000000000000000000000010000 ,
b00000000000000000000000000010000 -
b00000 /
b01010 0
b00000000000000000000000000000000 2
b00000000000000000000000000000000 3
b00000000000000000000000000001100 4
1U
b00000000000000000000000000001100 X
#85
0U
#86
b00000000000000000000000000010000 #
b00000000000101011000010110010011 $
b00000000000000000000000000000001 %
b00000000000000000000000000010001 +
b00000000000000000000000000010100 ,
b00000000000000000000000000010100 -
b00001 /
b01011 0
b00000000000000000000000000000001 3
b00000000000000000000000000001101 4
b00000000000000000000000000001100 ?
1U
#87
0U
#88
b00000000000000000000000000010100 #
b11111110011001011001100011100011 $
b11111111111111111111111111111000 %
0&
0'
1(
1)
b00000000000000000000000000001100 +
b00000000000000000000000000011000 ,
b00000000000000000000000000001100 -
b00110 /
b10001 0
b00000000000000000000000000001101 1
b00000000000000000000000011111111 2
b00000000000000000000000011111111 3
b00000000000000000000000100001100 4
b00000000000000000000000000001101 @
1U
b00000000000000000000000000001100 W
#89
0U
#90
b00000000000000000000000000001100 #
b00000000000001011000010100010011 $
b00000000000000000000000000000000 %
1&
1'
0(
0)
b00000000000000000000000000010000 ,
b00000000000000000000000000010000 -
b00000 /
b01010 0
b00000000000000000000000000000000 2
b00000000000000000000000000000000 3
b00000000000000000000000000001101 4
1U
b00000000000000000000000000001101 X
#91
0U
#92
b00000000000000000000000000010000 #
b00000000000101011000010110010011 $
b00000000000000000000000000000001 %
b00000000000000000000000000010001 +
b00000000000000000000000000010100 ,
b00000000000000000000000000010100 -
b00001 /
b01011 0
b00000000000000000000000000000001 3
b00000000000000000000000000001110 4
b00000000000000000000000000001101 ?
1U
#93
0U
#94
b00000000000000000000000000010100 #
b11111110011001011001100011100011 $
b11111111111111111111111111111000 %
0&
0'
1(
1)
b00000000000000000000000000001100 +
b00000000000000000000000000011000 ,
b00000000000000000000000000001100 -
b00110 /
b10001 0
b00000000000000000000000000001110 1
b00000000000000000000000011111111 2
b00000000000000000000000011111111 3
b00000000000000000000000100001101 4
b00000000000000000000000000001110 @
1U
b00000000000000000000000000001101 W
#95
0U
