Lab4-Reduced-RISC-V-with-lw/dataMemory.sv
module dataMemory #(
    parameter DATA_WIDTH = 32,
              ADDRESS_WIDTH = 32
             
)(
    input logic  [DATA_WIDTH-1:0]  A,
    input logic  [DATA_WIDTH-1:0]  WD,
    input logic                    WE,
    input logic                    clk,
    output logic [DATA_WIDTH-1:0]  RD
);

logic [7:0] sine_data [2**8-1:0];

initial begin
    $display("Loading Sine Data.");
    $readmemh("sinerom.mem", sine_data);
end;

assign RD = {{24{1'b0}}, sine_data[A[7:0]]};

always_ff @(posedge clk) begin
    if (WE) sine_data[A[7:0]] <= WD;
end

endmodule

LAB4_LOCAL/ALU.sv
module ALU #(
    parameter DATA_WIDTH = 32
)(
    input logic [DATA_WIDTH-1:0] ALUop1,
    input logic [DATA_WIDTH-1:0] ALUop2,
    //input logic ALUctrl,
    output logic [DATA_WIDTH-1:0] ALUout,
    output logic EQ 
);

assign EQ = (ALUop1==ALUop2);
assign ALUout = ALUop1 + ALUop2;

endmodule

LAB4_LOCAL/Reg_file.sv
module Reg_file #(
    parameter DATA_WIDTH = 32,
              ADD_WIDTH = 5
)(
    input logic [ADD_WIDTH-1:0] AD1,
    input logic [ADD_WIDTH-1:0] AD2,
    input logic [ADD_WIDTH-1:0] AD3,
    input logic [DATA_WIDTH-1:0] WD3,
    input logic WE3,
    input clk,
    output logic [DATA_WIDTH-1:0] RD1,
    output logic [DATA_WIDTH-1:0] RD2,
    output [DATA_WIDTH-1:0] a0, 
    output [DATA_WIDTH-1:0] a1    // added for debugging
);

logic [DATA_WIDTH-1:0] register [2**ADD_WIDTH-1:0];

// CHANGE NEEDED: read - async; write - sync
always_ff @(posedge clk) begin
    RD1 <= register[AD1];
    RD2 <= register[AD2];
    if(WE3) register[AD3] <= WD3;
    a0 <= register[5'd10];
    a1 <= register[5'd11];    // added for debugging
end

endmodule

LAB4_LOCAL/part2_top.sv
module part2_top #(
    parameter DATA_WIDTH = 32,
              ADD_WIDTH = 5
)(
    input logic clk,
    input logic [ADD_WIDTH-1:0] AD1,
    input logic [ADD_WIDTH-1:0] AD2,
    input logic [ADD_WIDTH-1:0] AD3,
    input logic WE3,
    input logic [DATA_WIDTH-1:0] WD3,
    input logic ALUsrc,
    input logic [DATA_WIDTH-1:0] Immop,
    output logic EQ,
    output logic [DATA_WIDTH-1:0] a0,
    output logic [DATA_WIDTH-1:0] a1,    // added for debugging
    output logic [DATA_WIDTH-1:0] rd2,
    output logic [DATA_WIDTH-1:0] ALUOUT
);

logic [DATA_WIDTH-1:0] RD1, RD2, ALUop2;

Reg_file REG (
    .AD1(AD1),
    .AD2(AD2),
    .AD3(AD3),
    .WE3(WE3),
    .WD3(WD3),
    .clk(clk),
    .a0(a0),
    .a1(a1),    // added for debugging
    .RD1(RD1),
    .RD2(RD2)
);

ALU ALU1 (
    .ALUop1(RD1),
    .ALUop2(ALUop2),
    .ALUout(ALUOUT),
    .EQ(EQ)
);

assign ALUop2 = ALUsrc? Immop : RD2;
assign rd2 = RD2;

endmodule

Lab4-Reduced-RISC-V-with-lw/signExtend.sv
module signExtend #(
    parameter WIDTH = 32
)(
    input logic  [WIDTH-1:0]  instr,
    input logic               ImmSrc,
    output logic [WIDTH-1:0]  ImmOp
);

    always_comb 
        case (ImmSrc)
            1'b0:          ImmOp = {{20{instr[31]}},instr[31:20]};  // IMMEDIATE
            // 3'b000:     ImmOp = {instr[31:12], 12{1'b0}};                //UPPER IMMEDIATE
            // 3'b000:     ImmOp = {20{instr[31]}, instr[31:25], intr[11:7]};       //STORE
            1'b1:          ImmOp = {{21{instr[31]}}, instr[7], instr[30:25], instr[11:8]};  // BRANCH
        endcase
endmodule

LAB4_LOCAL/controlUnit.sv
module controlUnit #(
    parameter WIDTH = 32
)(
    input logic  [WIDTH-1:0]    instr,
    input logic                 Eq,
    output logic                RegWrite,
    //output logic [2:0]          ALUctrl,
    output logic                ALUsrc,
    output logic                ImmSrc,
    output logic                PCsrc,
    output logic                MemWrite,
    output logic                ResultSrc
);

    always @ (instr) begin
        
        // addi
        if (instr[6:0] == 7'b0010011 && instr[14:12] == 3'b000) begin
            RegWrite <= 1'b1;
            // ALUctrl <= 1'b1;
            ALUsrc <= 1'b1;
            ImmSrc <= 1'b0;
            PCsrc <= 1'b0;
            MemWrite <= 1'b0;
            ResultSrc <= 1'b0;
        end

        // bne
        if (instr[6:0] == 7'b1100011 && instr[14:12] == 3'b001) begin
            RegWrite <= 1'b0;
            // ALUctrl <= 1'b1;
            ALUsrc <= 1'b0;
            ImmSrc <= 1'b1;
            PCsrc <= Eq ? 1'b0 : 1'b1;  // branch if not equal
            MemWrite <= 1'b0;
            ResultSrc <= 1'b0;
        end

        // lw
        if (instr[6:0] == 7'b0000011 && instr[14:12] == 3'b010) begin
            RegWrite <= 1'b1;
            // ALUctrl <= 1'b1;
            ALUsrc <= 1'b1;
            ImmSrc <= 1'b0;
            PCsrc <= 1'b0;
            MemWrite <= 1'b0;
            ResultSrc <= 1'b1;
        end

    end

endmodule

LAB4_LOCAL/instrMem.sv
module instrMem #(
    parameter WIDTH = 32
)(
    input logic [WIDTH - 1 : 0] A,
    output logic [WIDTH - 1: 0] RD

);

logic [7:0] rom_array [2**10-1:0];

initial begin
    $display("Loading ROM.");
    $readmemh("instrRom.mem", rom_array);
end;

always_comb
    //output is asynchronus
    RD = {rom_array[{A+{{30{1'b0}}, 2'b11}}], rom_array[{A+{{30{1'b0}}, 2'b10}}] ,rom_array[{A+{{31{1'b0}}, 1'b1}}], rom_array[A]};

endmodule

PC_REG.sv
module PC_REG #(
    parameter ADD_WIDTH = 32
)(
    input [ADD_WIDTH-1:0] Immop,
    input pcsrc,
    input clk,
    input rst,
    output [ADD_WIDTH-1:0] PC
);

logic [ADD_WIDTH-1:0] branch_pc, inc_pc, next_pc, tmp_pc;

assign branch_pc = tmp_pc + Immop;
assign inc_pc = tmp_pc + 32'd4;

assign next_pc = pcsrc ? branch_pc : inc_pc;

always_ff @(posedge clk) begin
    if (!rst)
        tmp_pc <= next_pc;
    else
        tmp_pc <= 32'b0;
end

assign PC = tmp_pc;
endmodule

Lab4-Reduced-RISC-V-with-lw/cpu_v2.sv
module cpu_v2 #(
    parameter A_WIDTH = 32,
              D_WIDTH = 32,
              rs1_LSB = 15,
              rs2_LSB = 20,
              rd_LSB = 7,
              ADD_WIDTH = 5
)(
    /// interface signals
    input logic                 clk,
    input logic                 rst,

    // data outputs from register file
    output logic [D_WIDTH-1:0]  a0, 
    output logic [D_WIDTH-1:0]  a1    // added for debugging
);

    /// interconnect wires
    logic   [A_WIDTH-1:0]        pc;      // program counter (PC)
    logic   [D_WIDTH-1:0]        instr;   // instruction
    logic   [D_WIDTH-1:0]        ImmOp;   // immediate operand (sign-extended)
        /// Control Unit outputs:
    logic                        RegWrite;
    logic                        ALUctrl;
    logic                        ALUsrc;
    logic                        ImmSrc;    // logic   [1:0]                ImmSrc;
    logic                        PCsrc;
        /// ALU block outputs:
    logic   [D_WIDTH-1:0]        ALUout;    
    logic                        eq;        // EQ
    logic   [D_WIDTH-1:0]        RD2;
    logic   [D_WIDTH-1:0]        ReadData;
    logic                        MemWrite;
    logic                        ResultSrc;

PC_REG PC_Reg (
    /// input
    .clk (clk),     // PC Reg clock
    .rst (rst),     // PC Reg reset
    .Immop (ImmOp),
    .pcsrc(PCsrc),
    /// output
    .PC (pc)
);

instrMem instr_mem (
    // input
    .A (pc),
    // output
    .RD (instr)
);

controlUnit control_unit (
    /// input
    .Eq (eq),
    .instr (instr),
    /// output
    .RegWrite (RegWrite),
    // .ALUctrl (ALUctrl),
    .ALUsrc (ALUsrc),
    .ImmSrc (ImmSrc),
    .PCsrc (PCsrc),
    .MemWrite(MemWrite),
    .ResultSrc(ResultSrc)
);

signExtend sign_extend(
    /// input
    .instr (instr),
    .ImmSrc (ImmSrc),
    /// output
    .ImmOp (ImmOp)
);

part2_top reg_file_alu (
    /// input 
    .clk (clk),              // Reg File clock
    .AD1 (instr[rs1_LSB+ADD_WIDTH-1 : rs1_LSB]),     // rs1 = instr[19:15]
    .AD2 (instr[rs2_LSB+ADD_WIDTH-1 : rs2_LSB]),     // rs2 = instr[24:20]
    .AD3 (instr[rd_LSB+ADD_WIDTH-1 : rd_LSB]),       //  rd = instr[11:7]
    .WE3 (RegWrite),
    .WD3 (ResultSrc ? ReadData : ALUout),   // WD3 = Result
    .ALUsrc (ALUsrc),
    // .ALUctrl (ALUctrl),
    .Immop (ImmOp),
    /// output
    .ALUOUT (ALUout),
    .EQ (eq),
    .a0 (a0),
    .a1(a1),    // added for debugging
    .rd2(RD2)

);

dataMemory data_memory(
    /// input
    .clk(clk),
    .A(ALUout),
    .WD(RD2),
    .WE(MemWrite),
    /// output
    .RD(ReadData)
);

endmodule

Lab4-Reduced-RISC-V-with-lw/cpu_v2.vcd
$version Generated by VerilatedVcd $end
$date Tue Dec  6 22:51:47 2022 $end
$timescale 1ps $end

 $scope module TOP $end
  $var wire 32 [ a0 [31:0] $end
  $var wire 32 \ a1 [31:0] $end
  $var wire  1 Y clk $end
  $var wire  1 Z rst $end
  $scope module cpu_v2 $end
   $var wire 32 a ADD_WIDTH [31:0] $end
   $var wire  1 b ALUctrl $end
   $var wire 32 * ALUout [31:0] $end
   $var wire  1 ' ALUsrc $end
   $var wire 32 ] A_WIDTH [31:0] $end
   $var wire 32 ] D_WIDTH [31:0] $end
   $var wire 32 % ImmOp [31:0] $end
   $var wire  1 ( ImmSrc $end
   $var wire  1 . MemWrite $end
   $var wire  1 ) PCsrc $end
   $var wire 32 , RD2 [31:0] $end
   $var wire 32 - ReadData [31:0] $end
   $var wire  1 & RegWrite $end
   $var wire  1 / ResultSrc $end
   $var wire 32 [ a0 [31:0] $end
   $var wire 32 \ a1 [31:0] $end
   $var wire  1 Y clk $end
   $var wire  1 + eq $end
   $var wire 32 $ instr [31:0] $end
   $var wire 32 # pc [31:0] $end
   $var wire 32 ` rd_LSB [31:0] $end
   $var wire 32 ^ rs1_LSB [31:0] $end
   $var wire 32 _ rs2_LSB [31:0] $end
   $var wire  1 Z rst $end
   $scope module PC_Reg $end
    $var wire 32 ] ADD_WIDTH [31:0] $end
    $var wire 32 % Immop [31:0] $end
    $var wire 32 # PC [31:0] $end
    $var wire 32 0 branch_pc [31:0] $end
    $var wire  1 Y clk $end
    $var wire 32 1 inc_pc [31:0] $end
    $var wire 32 2 next_pc [31:0] $end
    $var wire  1 ) pcsrc $end
    $var wire  1 Z rst $end
    $var wire 32 # tmp_pc [31:0] $end
   $upscope $end
   $scope module control_unit $end
    $var wire  1 ' ALUsrc $end
    $var wire  1 + Eq $end
    $var wire  1 ( ImmSrc $end
    $var wire  1 . MemWrite $end
    $var wire  1 ) PCsrc $end
    $var wire  1 & RegWrite $end
    $var wire  1 / ResultSrc $end
    $var wire 32 ] WIDTH [31:0] $end
    $var wire 32 $ instr [31:0] $end
   $upscope $end
   $scope module data_memory $end
    $var wire 32 * A [31:0] $end
    $var wire 32 ] ADDRESS_WIDTH [31:0] $end
    $var wire 32 ] DATA_WIDTH [31:0] $end
    $var wire 32 - RD [31:0] $end
    $var wire 32 , WD [31:0] $end
    $var wire  1 . WE $end
    $var wire  1 Y clk $end
   $upscope $end
   $scope module instr_mem $end
    $var wire 32 # A [31:0] $end
    $var wire 32 $ RD [31:0] $end
    $var wire 32 ] WIDTH [31:0] $end
   $upscope $end
   $scope module reg_file_alu $end
    $var wire  5 3 AD1 [4:0] $end
    $var wire  5 4 AD2 [4:0] $end
    $var wire  5 5 AD3 [4:0] $end
    $var wire 32 a ADD_WIDTH [31:0] $end
    $var wire 32 * ALUOUT [31:0] $end
    $var wire 32 8 ALUop2 [31:0] $end
    $var wire  1 ' ALUsrc $end
    $var wire 32 ] DATA_WIDTH [31:0] $end
    $var wire  1 + EQ $end
    $var wire 32 % Immop [31:0] $end
    $var wire 32 7 RD1 [31:0] $end
    $var wire 32 , RD2 [31:0] $end
    $var wire 32 6 WD3 [31:0] $end
    $var wire  1 & WE3 $end
    $var wire 32 [ a0 [31:0] $end
    $var wire 32 \ a1 [31:0] $end
    $var wire  1 Y clk $end
    $var wire 32 , rd2 [31:0] $end
    $scope module ALU1 $end
     $var wire 32 7 ALUop1 [31:0] $end
     $var wire 32 8 ALUop2 [31:0] $end
     $var wire 32 * ALUout [31:0] $end
     $var wire 32 ] DATA_WIDTH [31:0] $end
     $var wire  1 + EQ $end
    $upscope $end
    $scope module REG $end
     $var wire  5 3 AD1 [4:0] $end
     $var wire  5 4 AD2 [4:0] $end
     $var wire  5 5 AD3 [4:0] $end
     $var wire 32 a ADD_WIDTH [31:0] $end
     $var wire 32 ] DATA_WIDTH [31:0] $end
     $var wire 32 7 RD1 [31:0] $end
     $var wire 32 , RD2 [31:0] $end
     $var wire 32 6 WD3 [31:0] $end
     $var wire  1 & WE3 $end
     $var wire 32 [ a0 [31:0] $end
     $var wire 32 \ a1 [31:0] $end
     $var wire  1 Y clk $end
     $var wire 32 9 register[0] [31:0] $end
     $var wire 32 C register[10] [31:0] $end
     $var wire 32 D register[11] [31:0] $end
     $var wire 32 E register[12] [31:0] $end
     $var wire 32 F register[13] [31:0] $end
     $var wire 32 G register[14] [31:0] $end
     $var wire 32 H register[15] [31:0] $end
     $var wire 32 I register[16] [31:0] $end
     $var wire 32 J register[17] [31:0] $end
     $var wire 32 K register[18] [31:0] $end
     $var wire 32 L register[19] [31:0] $end
     $var wire 32 : register[1] [31:0] $end
     $var wire 32 M register[20] [31:0] $end
     $var wire 32 N register[21] [31:0] $end
     $var wire 32 O register[22] [31:0] $end
     $var wire 32 P register[23] [31:0] $end
     $var wire 32 Q register[24] [31:0] $end
     $var wire 32 R register[25] [31:0] $end
     $var wire 32 S register[26] [31:0] $end
     $var wire 32 T register[27] [31:0] $end
     $var wire 32 U register[28] [31:0] $end
     $var wire 32 V register[29] [31:0] $end
     $var wire 32 ; register[2] [31:0] $end
     $var wire 32 W register[30] [31:0] $end
     $var wire 32 X register[31] [31:0] $end
     $var wire 32 < register[3] [31:0] $end
     $var wire 32 = register[4] [31:0] $end
     $var wire 32 > register[5] [31:0] $end
     $var wire 32 ? register[6] [31:0] $end
     $var wire 32 @ register[7] [31:0] $end
     $var wire 32 A register[8] [31:0] $end
     $var wire 32 B register[9] [31:0] $end
    $upscope $end
   $upscope $end
   $scope module sign_extend $end
    $var wire 32 % ImmOp [31:0] $end
    $var wire  1 ( ImmSrc $end
    $var wire 32 ] WIDTH [31:0] $end
    $var wire 32 $ instr [31:0] $end
   $upscope $end
  $upscope $end
 $upscope $end
$enddefinitions $end


#0
b00000000000000000000000000000000 #
b00000000000000000000000000000000 $
b00000000000000000000000000000000 %
0&
0'
0(
0)
b00000000000000000000000000000000 *
1+
b00000000000000000000000000000000 ,
b00000000000000000000000000000000 -
0.
0/
b00000000000000000000000000000000 0
b00000000000000000000000000000100 1
b00000000000000000000000000000100 2
b00000 3
b00000 4
b00000 5
b00000000000000000000000000000000 6
b00000000000000000000000000000000 7
b00000000000000000000000000000000 8
b00000000000000000000000000000000 9
b00000000000000000000000000000000 :
b00000000000000000000000000000000 ;
b00000000000000000000000000000000 <
b00000000000000000000000000000000 =
b00000000000000000000000000000000 >
b00000000000000000000000000000000 ?
b00000000000000000000000000000000 @
b00000000000000000000000000000000 A
b00000000000000000000000000000000 B
b00000000000000000000000000000000 C
b00000000000000000000000000000000 D
b00000000000000000000000000000000 E
b00000000000000000000000000000000 F
b00000000000000000000000000000000 G
b00000000000000000000000000000000 H
b00000000000000000000000000000000 I
b00000000000000000000000000000000 J
b00000000000000000000000000000000 K
b00000000000000000000000000000000 L
b00000000000000000000000000000000 M
b00000000000000000000000000000000 N
b00000000000000000000000000000000 O
b00000000000000000000000000000000 P
b00000000000000000000000000000000 Q
b00000000000000000000000000000000 R
b00000000000000000000000000000000 S
b00000000000000000000000000000000 T
b00000000000000000000000000000000 U
b00000000000000000000000000000000 V
b00000000000000000000000000000000 W
b00000000000000000000000000000000 X
1Y
1Z
b00000000000000000000000000000000 [
b00000000000000000000000000000000 \
b00000000000000000000000000100000 ]
b00000000000000000000000000001111 ^
b00000000000000000000000000010100 _
b00000000000000000000000000000111 `
b00000000000000000000000000000101 a
0b
#1
b00001111111100000000001100010011 $
b00000000000000000000000011111111 %
1&
1'
b00000000000000000000000011111111 *
0+
b00000000000000000000000011111101 -
b00000000000000000000000011111111 0
b11111 4
b00110 5
b00000000000000000000000011111111 6
b00000000000000000000000011111111 8
0Y
#2
b00000000000000000000000011111111 ?
1Y
#3
0Y
#4
1Y
#5
0Y
#6
1Y
0Z
#7
0Y
#8
b00000000000000000000000000000100 #
b00000000000000000000010100010011 $
b00000000000000000000000000000000 %
b00000000000000000000000000000000 *
1+
b00000000000000000000000011111110 -
b00000000000000000000000000000100 0
b00000000000000000000000000001000 1
b00000000000000000000000000001000 2
b00000 4
b01010 5
b00000000000000000000000000000000 6
b00000000000000000000000000000000 8
1Y
#9
0Y
#10
b00000000000000000000000000001000 #
b00000000000000000000010110010011 $
b00000000000000000000000000001000 0
b00000000000000000000000000001100 1
b00000000000000000000000000001100 2
b01011 5
1Y
#11
0Y
#12
b00000000000000000000000000001100 #
b00000000000001011000010100010011 $
b00000000000000000000000000001100 0
b00000000000000000000000000010000 1
b00000000000000000000000000010000 2
b01011 3
b01010 5
1Y
#13
0Y
#14
b00000000000000000000000000010000 #
b00000000000101011000010110010011 $
b00000000000000000000000000000001 %
b00000000000000000000000000000001 *
0+
b00000000000000000000000011111101 -
b00000000000000000000000000010001 0
b00000000000000000000000000010100 1
b00000000000000000000000000010100 2
b00001 4
b01011 5
b00000000000000000000000000000001 6
b00000000000000000000000000000001 8
1Y
#15
0Y
#16
b00000000000000000000000000010100 #
b11111110011001011001100011100011 $
b11111111111111111111111111111000 %
0&
0'
1(
1)
b00000000000000000000000100000000 *
b00000000000000000000000011111111 ,
b00000000000000000000000011111110 -
b00000000000000000000000000001100 0
b00000000000000000000000000011000 1
b00000000000000000000000000001100 2
b00110 4
b10001 5
b00000000000000000000000100000000 6
b00000000000000000000000000000001 7
b00000000000000000000000011111111 8
b00000000000000000000000000000001 D
1Y
#17
0Y
#18
b00000000000000000000000000001100 #
b00000000000001011000010100010011 $
b00000000000000000000000000000000 %
1&
1'
0(
0)
b00000000000000000000000000000001 *
b00000000000000000000000000000000 ,
b00000000000000000000000011111101 -
b00000000000000000000000000010000 1
b00000000000000000000000000010000 2
b00000 4
b01010 5
b00000000000000000000000000000001 6
b00000000000000000000000000000000 8
1Y
b00000000000000000000000000000001 \
#19
0Y
#20
b00000000000000000000000000010000 #
b00000000000101011000010110010011 $
b00000000000000000000000000000001 %
b00000000000000000000000000000010 *
1+
b00000000000000000000000000010001 0
b00000000000000000000000000010100 1
b00000000000000000000000000010100 2
b00001 4
b01011 5
b00000000000000000000000000000010 6
b00000000000000000000000000000001 8
b00000000000000000000000000000001 C
1Y
#21
0Y
#22
b00000000000000000000000000010100 #
b11111110011001011001100011100011 $
b11111111111111111111111111111000 %
0&
0'
1(
1)
b00000000000000000000000100000001 *
0+
b00000000000000000000000011111111 ,
b00000000000000000000000000001100 0
b00000000000000000000000000011000 1
b00000000000000000000000000001100 2
b00110 4
b10001 5
b00000000000000000000000100000001 6
b00000000000000000000000000000010 7
b00000000000000000000000011111111 8
b00000000000000000000000000000010 D
1Y
b00000000000000000000000000000001 [
#23
0Y
#24
b00000000000000000000000000001100 #
b00000000000001011000010100010011 $
b00000000000000000000000000000000 %
1&
1'
0(
0)
b00000000000000000000000000000010 *
b00000000000000000000000000000000 ,
b00000000000000000000000000010000 1
b00000000000000000000000000010000 2
b00000 4
b01010 5
b00000000000000000000000000000010 6
b00000000000000000000000000000000 8
1Y
b00000000000000000000000000000010 \
#25
0Y
#26
b00000000000000000000000000010000 #
b00000000000101011000010110010011 $
b00000000000000000000000000000001 %
b00000000000000000000000000000011 *
b00000000000000000000000000010001 0
b00000000000000000000000000010100 1
b00000000000000000000000000010100 2
b00001 4
b01011 5
b00000000000000000000000000000011 6
b00000000000000000000000000000001 8
b00000000000000000000000000000010 C
1Y
#27
0Y
#28
b00000000000000000000000000010100 #
b11111110011001011001100011100011 $
b11111111111111111111111111111000 %
0&
0'
1(
1)
b00000000000000000000000100000010 *
b00000000000000000000000011111111 ,
b00000000000000000000000000001100 0
b00000000000000000000000000011000 1
b00000000000000000000000000001100 2
b00110 4
b10001 5
b00000000000000000000000100000010 6
b00000000000000000000000000000011 7
b00000000000000000000000011111111 8
b00000000000000000000000000000011 D
1Y
b00000000000000000000000000000010 [
#29
0Y
#30
b00000000000000000000000000001100 #
b00000000000001011000010100010011 $
b00000000000000000000000000000000 %
1&
1'
0(
0)
b00000000000000000000000000000011 *
b00000000000000000000000000000000 ,
b00000000000000000000000000010000 1
b00000000000000000000000000010000 2
b00000 4
b01010 5
b00000000000000000000000000000011 6
b00000000000000000000000000000000 8
1Y
b00000000000000000000000000000011 \
#31
0Y
#32
b00000000000000000000000000010000 #
b00000000000101011000010110010011 $
b00000000000000000000000000000001 %
b00000000000000000000000000000100 *
b00000000000000000000000000010001 0
b00000000000000000000000000010100 1
b00000000000000000000000000010100 2
b00001 4
b01011 5
b00000000000000000000000000000100 6
b00000000000000000000000000000001 8
b00000000000000000000000000000011 C
1Y
#33
0Y
#34
b00000000000000000000000000010100 #
b11111110011001011001100011100011 $
b11111111111111111111111111111000 %
0&
0'
1(
1)
b00000000000000000000000100000011 *
b00000000000000000000000011111111 ,
b00000000000000000000000000001100 0
b00000000000000000000000000011000 1
b00000000000000000000000000001100 2
b00110 4
b10001 5
b00000000000000000000000100000011 6
b00000000000000000000000000000100 7
b00000000000000000000000011111111 8
b00000000000000000000000000000100 D
1Y
b00000000000000000000000000000011 [
#35
0Y
#36
b00000000000000000000000000001100 #
b00000000000001011000010100010011 $
b00000000000000000000000000000000 %
1&
1'
0(
0)
b00000000000000000000000000000100 *
b00000000000000000000000000000000 ,
b00000000000000000000000000010000 1
b00000000000000000000000000010000 2
b00000 4
b01010 5
b00000000000000000000000000000100 6
b00000000000000000000000000000000 8
1Y
b00000000000000000000000000000100 \
#37
0Y
#38
b00000000000000000000000000010000 #
b00000000000101011000010110010011 $
b00000000000000000000000000000001 %
b00000000000000000000000000000101 *
b00000000000000000000000000010001 0
b00000000000000000000000000010100 1
b00000000000000000000000000010100 2
b00001 4
b01011 5
b00000000000000000000000000000101 6
b00000000000000000000000000000001 8
b00000000000000000000000000000100 C
1Y
#39
0Y
#40
b00000000000000000000000000010100 #
b11111110011001011001100011100011 $
b11111111111111111111111111111000 %
0&
0'
1(
1)
b00000000000000000000000100000100 *
b00000000000000000000000011111111 ,
b00000000000000000000000000001100 0
b00000000000000000000000000011000 1
b00000000000000000000000000001100 2
b00110 4
b10001 5
b00000000000000000000000100000100 6
b00000000000000000000000000000101 7
b00000000000000000000000011111111 8
b00000000000000000000000000000101 D
1Y
b00000000000000000000000000000100 [
#41
0Y
#42
b00000000000000000000000000001100 #
b00000000000001011000010100010011 $
b00000000000000000000000000000000 %
1&
1'
0(
0)
b00000000000000000000000000000101 *
b00000000000000000000000000000000 ,
b00000000000000000000000000010000 1
b00000000000000000000000000010000 2
b00000 4
b01010 5
b00000000000000000000000000000101 6
b00000000000000000000000000000000 8
1Y
b00000000000000000000000000000101 \
#43
0Y
#44
b00000000000000000000000000010000 #
b00000000000101011000010110010011 $
b00000000000000000000000000000001 %
b00000000000000000000000000000110 *
b00000000000000000000000011111100 -
b00000000000000000000000000010001 0
b00000000000000000000000000010100 1
b00000000000000000000000000010100 2
b00001 4
b01011 5
b00000000000000000000000000000110 6
b00000000000000000000000000000001 8
b00000000000000000000000000000101 C
1Y
#45
0Y
#46
b00000000000000000000000000010100 #
b11111110011001011001100011100011 $
b11111111111111111111111111111000 %
0&
0'
1(
1)
b00000000000000000000000100000101 *
b00000000000000000000000011111111 ,
b00000000000000000000000011111101 -
b00000000000000000000000000001100 0
b00000000000000000000000000011000 1
b00000000000000000000000000001100 2
b00110 4
b10001 5
b00000000000000000000000100000101 6
b00000000000000000000000000000110 7
b00000000000000000000000011111111 8
b00000000000000000000000000000110 D
1Y
b00000000000000000000000000000101 [
#47
0Y
#48
b00000000000000000000000000001100 #
b00000000000001011000010100010011 $
b00000000000000000000000000000000 %
1&
1'
0(
0)
b00000000000000000000000000000110 *
b00000000000000000000000000000000 ,
b00000000000000000000000011111100 -
b00000000000000000000000000010000 1
b00000000000000000000000000010000 2
b00000 4
b01010 5
b00000000000000000000000000000110 6
b00000000000000000000000000000000 8
1Y
b00000000000000000000000000000110 \
#49
0Y
#50
b00000000000000000000000000010000 #
b00000000000101011000010110010011 $
b00000000000000000000000000000001 %
b00000000000000000000000000000111 *
b00000000000000000000000000010001 0
b00000000000000000000000000010100 1
b00000000000000000000000000010100 2
b00001 4
b01011 5
b00000000000000000000000000000111 6
b00000000000000000000000000000001 8
b00000000000000000000000000000110 C
1Y
#51
0Y
#52
b00000000000000000000000000010100 #
b11111110011001011001100011100011 $
b11111111111111111111111111111000 %
0&
0'
1(
1)
b00000000000000000000000100000110 *
b00000000000000000000000011111111 ,
b00000000000000000000000000001100 0
b00000000000000000000000000011000 1
b00000000000000000000000000001100 2
b00110 4
b10001 5
b00000000000000000000000100000110 6
b00000000000000000000000000000111 7
b00000000000000000000000011111111 8
b00000000000000000000000000000111 D
1Y
b00000000000000000000000000000110 [
#53
0Y
#54
b00000000000000000000000000001100 #
b00000000000001011000010100010011 $
b00000000000000000000000000000000 %
1&
1'
0(
0)
b00000000000000000000000000000111 *
b00000000000000000000000000000000 ,
b00000000000000000000000000010000 1
b00000000000000000000000000010000 2
b00000 4
b01010 5
b00000000000000000000000000000111 6
b00000000000000000000000000000000 8
1Y
b00000000000000000000000000000111 \
#55
0Y
#56
b00000000000000000000000000010000 #
b00000000000101011000010110010011 $
b00000000000000000000000000000001 %
b00000000000000000000000000001000 *
b00000000000000000000000011111011 -
b00000000000000000000000000010001 0
b00000000000000000000000000010100 1
b00000000000000000000000000010100 2
b00001 4
b01011 5
b00000000000000000000000000001000 6
b00000000000000000000000000000001 8
b00000000000000000000000000000111 C
1Y
#57
0Y
#58
b00000000000000000000000000010100 #
b11111110011001011001100011100011 $
b11111111111111111111111111111000 %
0&
0'
1(
1)
b00000000000000000000000100000111 *
b00000000000000000000000011111111 ,
b00000000000000000000000011111100 -
b00000000000000000000000000001100 0
b00000000000000000000000000011000 1
b00000000000000000000000000001100 2
b00110 4
b10001 5
b00000000000000000000000100000111 6
b00000000000000000000000000001000 7
b00000000000000000000000011111111 8
b00000000000000000000000000001000 D
1Y
b00000000000000000000000000000111 [
#59
0Y
#60
b00000000000000000000000000001100 #
b00000000000001011000010100010011 $
b00000000000000000000000000000000 %
1&
1'
0(
0)
b00000000000000000000000000001000 *
b00000000000000000000000000000000 ,
b00000000000000000000000011111011 -
b00000000000000000000000000010000 1
b00000000000000000000000000010000 2
b00000 4
b01010 5
b00000000000000000000000000001000 6
b00000000000000000000000000000000 8
1Y
b00000000000000000000000000001000 \
#61
0Y
#62
b00000000000000000000000000010000 #
b00000000000101011000010110010011 $
b00000000000000000000000000000001 %
b00000000000000000000000000001001 *
b00000000000000000000000011111010 -
b00000000000000000000000000010001 0
b00000000000000000000000000010100 1
b00000000000000000000000000010100 2
b00001 4
b01011 5
b00000000000000000000000000001001 6
b00000000000000000000000000000001 8
b00000000000000000000000000001000 C
1Y
#63
0Y
#64
b00000000000000000000000000010100 #
b11111110011001011001100011100011 $
b11111111111111111111111111111000 %
0&
0'
1(
1)
b00000000000000000000000100001000 *
b00000000000000000000000011111111 ,
b00000000000000000000000011111011 -
b00000000000000000000000000001100 0
b00000000000000000000000000011000 1
b00000000000000000000000000001100 2
b00110 4
b10001 5
b00000000000000000000000100001000 6
b00000000000000000000000000001001 7
b00000000000000000000000011111111 8
b00000000000000000000000000001001 D
1Y
b00000000000000000000000000001000 [
#65
0Y
#66
b00000000000000000000000000001100 #
b00000000000001011000010100010011 $
b00000000000000000000000000000000 %
1&
1'
0(
0)
b00000000000000000000000000001001 *
b00000000000000000000000000000000 ,
b00000000000000000000000011111010 -
b00000000000000000000000000010000 1
b00000000000000000000000000010000 2
b00000 4
b01010 5
b00000000000000000000000000001001 6
b00000000000000000000000000000000 8
1Y
b00000000000000000000000000001001 \
#67
0Y
#68
b00000000000000000000000000010000 #
b00000000000101011000010110010011 $
b00000000000000000000000000000001 %
b00000000000000000000000000001010 *
b00000000000000000000000000010001 0
b00000000000000000000000000010100 1
b00000000000000000000000000010100 2
b00001 4
b01011 5
b00000000000000000000000000001010 6
b00000000000000000000000000000001 8
b00000000000000000000000000001001 C
1Y
#69
0Y
#70
b00000000000000000000000000010100 #
b11111110011001011001100011100011 $
b11111111111111111111111111111000 %
0&
0'
1(
1)
b00000000000000000000000100001001 *
b00000000000000000000000011111111 ,
b00000000000000000000000000001100 0
b00000000000000000000000000011000 1
b00000000000000000000000000001100 2
b00110 4
b10001 5
b00000000000000000000000100001001 6
b00000000000000000000000000001010 7
b00000000000000000000000011111111 8
b00000000000000000000000000001010 D
1Y
b00000000000000000000000000001001 [
#71
0Y
#72
b00000000000000000000000000001100 #
b00000000000001011000010100010011 $
b00000000000000000000000000000000 %
1&
1'
0(
0)
b00000000000000000000000000001010 *
b00000000000000000000000000000000 ,
b00000000000000000000000000010000 1
b00000000000000000000000000010000 2
b00000 4
b01010 5
b00000000000000000000000000001010 6
b00000000000000000000000000000000 8
1Y
b00000000000000000000000000001010 \
#73
0Y
